neulab/__init__.py
neulab/Dataframe/__init__.py
neulab/Dataframe/clusters.py
neulab/Dataframe/discover.py
neulab/Dataframe/importance.py
neulab/Dataframe/normalization.py
neulab/Dataframe/outliers.py
neulab/Dataframe/recover.py
neulab/Vector/__init__.py
neulab/Vector/clusters.py
neulab/Vector/discover.py
neulab/Vector/normalization.py
neulab/Vector/outliers.py
neulab/Vector/recover.py
neulab-0.1.1.dist-info/LICENSE
neulab-0.1.1.dist-info/METADATA
neulab-0.1.1.dist-info/WHEEL
neulab-0.1.1.dist-info/top_level.txt
neulab-0.1.1.dist-info/RECORD
