Metadata-Version: 2.1
Name: neulab
Version: 0.1.1
Summary: Tool for data preprocess in ML.
Home-page: https://github.com/kndahl/neulab
Author: Roman Fitzjalen
Author-email: romaactor@gmail.com
License: MIT
Platform: UNKNOWN
License-File: LICENSE
Requires-Dist: numpy
Requires-Dist: pandas
Requires-Dist: scipy
Requires-Dist: networkx
Requires-Dist: matplotlib
Requires-Dist: jinja2
Requires-Dist: seaborn
Requires-Dist: scikit-learn
